representations/__init__.py
representations/bin/__init__.py
representations/bin/abstract_serializable.py
representations/bin/action.py
representations/bin/entity.py
representations/bin/link.py
representations/bin/property.py
representations/bin/representation.py
representations/bin/resource_class.py
representations/bin/siren_object.py
representations/bin/siren_object_api_impl.py
representations/bin/types/__init__.py
representations/bin/types/json.py
representations/libs/__init__.py
representations/libs/exceptions.py
representations/libs/utils/__init__.py
representations/libs/utils/body.py
representations/tests/__init__.py
representations/tests/fixtures.py
representations/tests/helpers.py
representations/tests/test_action.py
representations/tests/test_body.py
representations/tests/test_json.py
representations/tests/test_links.py
representations/tests/test_representations.py
representations-1.0.3.dist-info/DESCRIPTION.rst
representations-1.0.3.dist-info/METADATA
representations-1.0.3.dist-info/RECORD
representations-1.0.3.dist-info/WHEEL
representations-1.0.3.dist-info/metadata.json
representations-1.0.3.dist-info/top_level.txt
