Metadata-Version: 2.0
Name: representations
Version: 1.0.3
Summary: A tool for building of siren representations.
Home-page: UNKNOWN
Author: atomikin
Author-email: UNKNOWN
License: UNKNOWN
Platform: any
